Metadata-Version: 2.1
Name: htbapi
Version: 1.3
Summary: An unofficial API Wrapper for Hackthebox.
Home-page: https://gitlab.com/sw1tchbl4d3/htbapi
Author: sw1tchbl4d3
Author-email: jsimeze@pm.me
License: GPL
Platform: UNKNOWN
